LICENSE
MANIFEST.in
README.rst
setup.py
django_grafico_db.egg-info/PKG-INFO
django_grafico_db.egg-info/SOURCES.txt
django_grafico_db.egg-info/dependency_links.txt
django_grafico_db.egg-info/requires.txt
django_grafico_db.egg-info/top_level.txt
grafico_db/__init__.py
grafico_db/admin.py
grafico_db/apps.py
grafico_db/models.py
grafico_db/tests.py
grafico_db/urls.py
grafico_db/views.py
grafico_db/migrations/__init__.py
grafico_db/static/grafico_db/info
grafico_db/templates/index.html