Metadata-Version: 1.1
Name: django-grafico-db
Version: 1.0
Summary: UNKNOWN
Home-page: UNKNOWN
Author: Manuel Machacón Cantillo
Author-email: machaconmanuel@gmail.com
License: BSD License
Keywords: sample setuptools development django-extensions,database,db-graphviz,sql,orm,pydot
Platform: UNKNOWN
Classifier: Environment :: Web Environment
Classifier: Framework :: Django
Classifier: Framework :: Django :: 1.10
Classifier: Intended Audience :: Developers
Classifier: License :: Free To Use But Restricted
Classifier: Operating System :: Unix
Classifier: Programming Language :: Python :: 2.7
Classifier: Topic :: Internet :: WWW/HTTP
Classifier: Topic :: Internet :: WWW/HTTP :: Dynamic Content
